fasthtml_extn/__init__.py
fasthtml_extn/components.py
fasthtml_extn/libraries/icons.py
fasthtml_extn/libraries/tailwind.py
fasthtml_extn/utils.py
fasthtml_extn-0.1.0.dist-info/LICENCE
fasthtml_extn-0.1.0.dist-info/METADATA
fasthtml_extn-0.1.0.dist-info/WHEEL
fasthtml_extn-0.1.0.dist-info/RECORD
