Metadata-Version: 2.1
Name: fasthtml_extn
Version: 0.1.0
Summary: An fasthtml extension framework to build webapps using python.
Author: Jose Antonio Dominguez
Author-email: chamot11@gmail.com
Requires-Python: >=3.11,<4.0
Classifier: Programming Language :: Python :: 3
Classifier: Programming Language :: Python :: 3.11
Classifier: Programming Language :: Python :: 3.12
Requires-Dist: python-fasthtml (>=0.5.1,<0.6.0)
